{"flow":{"onboarding":{"$contentActions":[{"input":{"bypass":false,"$cardContent":{"document":{"id":"252dbbd6-b37f-4493-9c66-2a0e1f031d98","type":"text/plain","content":"Entrada do usuário"},"editable":false,"deletable":false,"position":"right","editing":false},"$invalid":false},"$invalid":false}],"$conditionOutputs":[{"stateId":"{{blockDestinationId}}","typeOfStateId":"variable","$id":"2ea47fda-f02e-4cb9-a540-7a3c9add4168","conditions":[{"source":"context","comparison":"notEquals","values":["false"],"variable":"blockDestinationId"}],"$invalid":false},{"stateId":"welcome","conditions":[{"source":"input","comparison":"matches","values":[".*"]}],"$id":"0a06cefe-117c-480f-8dad-bef8fdeb3d3e","$connId":"con_3","$invalid":false}],"$enteringCustomActions":[],"$leavingCustomActions":[{"$id":"d3b82733-a776-4ee9-916d-e5422b12d3af","$typeOfContent":"","type":"ExecuteScript","$title":"Process \"blockDestinationId\"","$invalid":false,"settings":{"function":"run","source":"function run(state, serviceName) {\n\ttry {\n\t\tconst { botDestination, stateDestination } = JSON.parse(state)\n\n\t\tif (stateDestination.match(/^[0-9a-fA-F]{8}\\b-[0-9a-fA-F]{4}\\b-[0-9a-fA-F]{4}\\b-[0-9a-fA-F]{4}\\b-[0-9a-fA-F]{12}$/) && botDestination === serviceName) {\n\t\t\treturn stateDestination\n\t\t}\n\t\treturn false\n\t} catch (err) {\n\t\treturn false\n\t}\n}","inputVariables":["state","config.serviceName"],"outputVariable":"blockDestinationId","LocalTimeZoneEnabled":false},"conditions":[]}],"$inputSuggestions":[],"$defaultOutput":{"stateId":"fallback","$invalid":false},"isAiGenerated":false,"$tags":[{"id":"blip-tag-c54d1017-196f-44ea-8191-f53c0f43cfcd","label":"ExecuteScript","background":"#FF961E","canChangeBackground":false},{"id":"blip-tag-0cbd81f9-aac7-4c95-a8c3-a4e8219d98a1","label":"UserInput","background":"#000000","canChangeBackground":false}],"id":"onboarding","root":true,"$title":"Início","$position":{"top":"192px","left":"703px"},"$invalidContentActions":false,"$invalidOutputs":false,"$invalidCustomActions":false,"$invalid":false},"fallback":{"$contentActions":[{"input":{"bypass":true,"$cardContent":{"document":{"id":"7f9c45f2-07ff-4eea-b5d2-54025bf7b400","type":"text/plain"},"editable":false,"deletable":true,"position":"right","editing":false},"$invalid":false},"$invalid":false}],"$conditionOutputs":[{"stateId":"error","conditions":[{"source":"input","comparison":"matches","values":[".*"]}],"$id":"05a0fd9b-f6b2-4a87-9fa8-f4857aca21fa","$connId":"con_8","$invalid":false}],"$enteringCustomActions":[],"$leavingCustomActions":[],"$inputSuggestions":[],"$defaultOutput":{"stateId":"onboarding","$invalid":false},"isAiGenerated":false,"$tags":[],"id":"fallback","$title":"Exceções","$position":{"top":"77px","left":"1561px"},"$invalidContentActions":false,"$invalidOutputs":false,"$invalidCustomActions":false,"$invalid":false},"welcome":{"$contentActions":[{"input":{"bypass":true,"$cardContent":{"document":{"id":"6e1d4832-050e-4133-8da2-c0bbf0d541bc","type":"text/plain","content":"Entrada do usuário"},"editable":false,"deletable":true,"position":"right","editing":false},"$invalid":false},"$invalid":false}],"$conditionOutputs":[{"stateId":"723cfa31-6e62-457c-808f-058dc7ddc66a","typeOfStateId":"state","$connId":"con_13","$id":"7c50d3d1-2d8a-41ae-aceb-7a0f442cd3b8","conditions":[{"source":"context","comparison":"exists","values":[],"variable":"contaSelecionada@segmentoGerente"}],"$invalid":false},{"stateId":"4e573405-55d0-4da8-8ba3-52234cfb12a0","typeOfStateId":"state","$connId":"con_18","$id":"eb90e6f8-288c-4ff3-b3d6-79180d18912d","conditions":[{"source":"input","comparison":"exists","values":[]}],"$invalid":false}],"$enteringCustomActions":[],"$leavingCustomActions":[],"$inputSuggestions":[],"$defaultOutput":{"stateId":"fallback","$invalid":false},"isAiGenerated":false,"$tags":[],"id":"welcome","$title":"[AH.0.0.0] Valida segmento (PJ|Gerentes)","$position":{"top":"368px","left":"703px"},"$invalidContentActions":false,"$invalidOutputs":false,"$invalidCustomActions":false,"$invalid":false},"error":{"$contentActions":[{"action":{"$id":"01b8083e-9389-4ca7-91b0-d8990b31f72a","$typeOfContent":"","type":"SendMessage","settings":{"id":"00000000-0000-0000-0000-000000000002","type":"application/vnd.lime.chatstate+json","content":{"state":"composing","interval":1000}},"$cardContent":{"document":{"id":"00000000-0000-0000-0000-000000000002","type":"application/vnd.lime.chatstate+json","content":{"state":"composing","interval":1000}},"editable":true,"deletable":true,"position":"left","editing":false}},"$invalid":false},{"action":{"$id":"c8acddcc-a1e8-40e0-852c-40157c186304","$typeOfContent":"","type":"SendMessage","settings":{"id":"00000000-0000-0000-0000-000000000003","type":"text/plain","content":"Desculpe, não consegui entender!"},"$cardContent":{"document":{"id":"00000000-0000-0000-0000-000000000003","type":"text/plain","content":"Desculpe, não consegui entender!"},"editable":true,"deletable":true,"position":"left","editing":false}},"$invalid":false},{"input":{"bypass":true,"$cardContent":{"document":{"id":"1fef7059-7489-4368-8ba0-52602ef029d4","type":"text/plain"},"editable":false,"deletable":true,"position":"right","editing":false},"$invalid":false},"$invalid":false}],"$conditionOutputs":[],"$enteringCustomActions":[],"$leavingCustomActions":[],"$inputSuggestions":[],"$defaultOutput":{"stateId":"onboarding","$invalid":false},"isAiGenerated":false,"$tags":[{"id":"blip-tag-f631fdbf-630f-4d4b-8b9d-070982fabab8","label":"SendMessage","background":"#EE82EE","canChangeBackground":false}],"id":"error","$title":"Erro padrão","$position":{"top":"66px","left":"1785px"},"$invalidContentActions":false,"$invalidOutputs":false,"$invalidCustomActions":false,"$invalid":false},"4e573405-55d0-4da8-8ba3-52234cfb12a0":{"$contentActions":[{"input":{"bypass":true,"$cardContent":{"document":{"id":"3baef588-be0b-48dd-9bd7-aad73bb79928","type":"text/plain","textContent":"Entrada do usuário","content":"Entrada do usuário"},"editable":false,"deletable":true,"position":"right","editing":false},"$invalid":false},"$invalid":false}],"$conditionOutputs":[{"stateId":"c7d220bd-2237-49f4-88ec-14c555bf202c","typeOfStateId":"state","$connId":"con_23","$id":"2ec9229c-0eff-46ad-99e8-6215ae8d9de7","conditions":[{"source":"input","comparison":"exists","values":[]}],"$invalid":false}],"$enteringCustomActions":[],"$leavingCustomActions":[],"$inputSuggestions":[],"$defaultOutput":{"stateId":"fallback","$invalid":false},"isAiGenerated":false,"$tags":[],"id":"4e573405-55d0-4da8-8ba3-52234cfb12a0","root":false,"$title":"[AH.1.0.0] Atendimento PJ","$position":{"top":"602px","left":"1516px"},"$invalidContentActions":false,"$invalidOutputs":false,"$invalidCustomActions":false,"$invalid":false},"723cfa31-6e62-457c-808f-058dc7ddc66a":{"$contentActions":[{"input":{"bypass":true,"$cardContent":{"document":{"id":"34902f40-4eef-4315-917a-803d34c9ba2f","type":"text/plain","textContent":"Entrada do usuário","content":"Entrada do usuário"},"editable":false,"deletable":true,"position":"right","editing":false},"$invalid":false},"$invalid":false}],"$conditionOutputs":[{"stateId":"5a9c72b7-bfaf-4105-86c1-9cf8be316c37","typeOfStateId":"state","$connId":"con_28","$id":"4b4cdbc2-fa9e-442f-b1c9-63fa70a4a783","conditions":[{"source":"context","comparison":"equals","values":["emp1"],"variable":"contaSelecionada@segmentoGerente"}],"$invalid":false},{"stateId":"9a6f3021-b73e-4a50-8ada-691ed5fecfd8","typeOfStateId":"state","$connId":"con_33","$id":"a4c58c7e-4bd8-4b80-bd9e-2751a6fff41e","conditions":[{"source":"input","comparison":"exists","values":[]}],"$invalid":false}],"$enteringCustomActions":[],"$leavingCustomActions":[],"$inputSuggestions":[],"$defaultOutput":{"stateId":"fallback","$invalid":false},"isAiGenerated":false,"$tags":[],"id":"723cfa31-6e62-457c-808f-058dc7ddc66a","root":false,"$title":"[AH.2.0.0] Atendimento Gerentes","$position":{"top":"603px","left":"703px"},"$invalidContentActions":false,"$invalidOutputs":false,"$invalidCustomActions":false,"$invalid":false},"6fa758ab-c567-4f4d-936e-7e524c091892":{"$contentActions":[{"action":{"type":"SendMessage","settings":{"id":"00d88841-5e7e-45de-9367-198de9ea8e6b","type":"application/vnd.lime.chatstate+json","content":{"state":"composing","interval":1000}},"$cardContent":{"document":{"id":"00d88841-5e7e-45de-9367-198de9ea8e6b","type":"application/vnd.lime.chatstate+json","content":{"state":"composing","interval":1000}},"editable":true,"deletable":true,"position":"left"}},"$invalid":false},{"action":{"type":"SendMessage","settings":{"id":"80bc5452-d74d-441e-a85f-4e9a7a6b16e7","type":"text/plain","content":"O horário de atendimento do Gerente Safra Empresas é de segunda à sexta-feira das 09 às 18 horas, exceto feriados. \n\nA Central de Atendimento \nPessoa Jurídica pode ajudar. \n\nPara capitais e Grande São Paulo ligue (11) 3175-8248 e demais localidades ligue 0300 015 7575. \n\nEstamos à sua disposição. \nObrigado!","metadata":{}},"$cardContent":{"document":{"id":"80bc5452-d74d-441e-a85f-4e9a7a6b16e7","type":"text/plain","content":"O horário de atendimento do Gerente Safra Empresas é de segunda à sexta-feira das 09 às 18 horas, exceto feriados. \n\nA Central de Atendimento \nPessoa Jurídica pode ajudar. \n\nPara capitais e Grande São Paulo ligue (11) 3175-8248 e demais localidades ligue 0300 015 7575. \n\nEstamos à sua disposição. \nObrigado!"},"editable":true,"deletable":true,"position":"left"}},"$invalid":false},{"input":{"bypass":true,"$cardContent":{"document":{"id":"fd1c385b-7adc-4efb-b829-3b137d4e97c0","type":"text/plain","textContent":"Entrada do usuário","content":"Entrada do usuário"},"editable":false,"deletable":true,"position":"right"},"$invalid":false},"$invalid":false}],"$conditionOutputs":[],"$enteringCustomActions":[],"$leavingCustomActions":[],"$inputSuggestions":[],"$defaultOutput":{"stateId":"105470a0-0131-4cdb-9db2-b60e0997a97b","$invalid":false,"typeOfStateId":"state"},"id":"6fa758ab-c567-4f4d-936e-7e524c091892","root":false,"$title":"[AH.2.3.0] Fora do horario de atendimento","$position":{"top":"998px","left":"508px"},"$invalidContentActions":false,"$invalidOutputs":false,"$invalidCustomActions":false,"$invalid":false,"$tags":[{"id":"blip-tag-43d2d649-1b12-43cc-854f-368bcef83670","label":"SendMessage","background":"#EE82EE","canChangeBackground":false}],"isAiGenerated":false},"bf1d18c3-7de4-4f75-8817-239b4fcf993c":{"$contentActions":[{"action":{"$id":"6e13eac5-fc9c-49df-a244-6baa2ef031b0","type":"SendMessage","settings":{"id":"c4f46f4c-ec10-47ad-bd24-3ffd077aa4ad","type":"application/vnd.lime.chatstate+json","content":{"state":"composing","interval":1000}},"$cardContent":{"document":{"id":"c4f46f4c-ec10-47ad-bd24-3ffd077aa4ad","type":"application/vnd.lime.chatstate+json","content":{"state":"composing","interval":1000}},"editable":true,"deletable":true,"position":"left"}},"$invalid":false},{"action":{"$id":"7fde6a79-d777-480b-8b47-30fc27ac8363","type":"SendMessage","settings":{"id":"9665efe7-68a1-4825-8aba-6f4f5ba46ccf","type":"text/plain","content":"Aguarde, você está sendo direcionado para seu gerente.","metadata":{}},"$cardContent":{"document":{"id":"9665efe7-68a1-4825-8aba-6f4f5ba46ccf","type":"text/plain","content":"Aguarde, você está sendo direcionado para seu gerente."},"editable":true,"deletable":true,"position":"left"}},"$invalid":false},{"input":{"bypass":true,"$cardContent":{"document":{"id":"4fb59875-a2a3-4d4d-b35f-bcb11ff38d46","type":"text/plain","textContent":"Entrada do usuário","content":"Entrada do usuário"},"editable":false,"deletable":true,"position":"right","editing":false},"$invalid":false},"$invalid":false}],"$conditionOutputs":[{"stateId":"1d08cfc6-9698-4d24-a308-9bb5e400957f","typeOfStateId":"state","$connId":"con_38","$id":"2f1a0e23-54c7-438a-a8b9-e6e59b29d8d3","conditions":[{"source":"input","comparison":"exists","values":[]}],"$invalid":false}],"$enteringCustomActions":[],"$leavingCustomActions":[{"$id":"a53ca151-6fd2-4cd6-accb-a14de3ac1037","$typeOfContent":"","type":"MergeContact","$title":"Set \"team\" to \"{contaSelecionada@filaGerente}\"","$invalid":false,"settings":{"extras":{"team":"{{contaSelecionada@filaGerente}}"}},"conditions":[]},{"$id":"4e622200-43e6-4594-97cc-ad409b0d503f","$typeOfContent":"","type":"MergeContact","$title":"Set \"team\" if \"broadcast\"","$invalid":false,"settings":{"extras":{"team":"Default"}},"conditions":[{"values":["reativacao_emp1","reativacao_emp1_v2"],"source":"context","comparison":"equals","variable":"contact.extras.broadcastOrigem"}]},{"$id":"b3c31a6d-2b9c-4517-bbaa-e963a099e245","type":"SetVariable","$title":"Set \"tunnelMain\" to \"{tunnel.identity}\"","$invalid":false,"settings":{"variable":"tunnelMain","value":"{{tunnel.identity}}"},"conditions":[]}],"$inputSuggestions":[],"$defaultOutput":{"stateId":"onboarding","$invalid":false,"typeOfStateId":"state"},"$tags":[{"id":"blip-tag-c08cad5e-78a6-41c2-9092-9921d3891de7","label":"MergeContact","background":"#FF1E90","canChangeBackground":false},{"id":"blip-tag-d15f94b8-93d9-41ed-8acb-a8eb6ea51ce8","label":"SetVariable","background":"#FF4A1E","canChangeBackground":false},{"id":"blip-tag-bdd7fe79-7fe5-4855-8ddd-c0c3af54fb49","label":"SendMessage","background":"#EE82EE","canChangeBackground":false}],"id":"bf1d18c3-7de4-4f75-8817-239b4fcf993c","root":false,"$title":"[AH.2.4.0] Define fila de atendimento","$position":{"top":"960px","left":"1026px"},"$invalidContentActions":false,"$invalidOutputs":false,"$invalidCustomActions":false,"$invalid":false,"isAiGenerated":false},"5a9c72b7-bfaf-4105-86c1-9cf8be316c37":{"$contentActions":[{"input":{"bypass":true,"$cardContent":{"document":{"id":"9c0f606a-c029-4381-89c3-726e5df5c07e","type":"text/plain","textContent":"Entrada do usuário","content":"Entrada do usuário"},"editable":false,"deletable":true,"position":"right","editing":false},"$invalid":false},"$invalid":false}],"$conditionOutputs":[{"stateId":"bf1d18c3-7de4-4f75-8817-239b4fcf993c","$connId":"con_43","conditions":[{"source":"context","comparison":"equals","variable":"isWorkTime","values":["true"]}],"$invalid":false,"$id":"77727111-c15f-4795-9b2f-163be66ffac7","typeOfStateId":"state"},{"stateId":"6fa758ab-c567-4f4d-936e-7e524c091892","$connId":"con_48","conditions":[{"source":"context","comparison":"equals","values":["false"],"variable":"isWorkTime"}],"$invalid":false,"$id":"6412da4c-8e08-4fc1-a1d7-33f6bde1b36f"}],"$enteringCustomActions":[{"$id":"ad5b301e-f8b8-46e1-8c6e-d10d95682442","$typeOfContent":"","type":"ProcessHttp","$title":"Requisição HTTP horario","$invalid":false,"settings":{"headers":{"Authorization":"Bearer {{bodyToken@access_token}}","User-Agent":"Fiddler","Content-Type":"application/json"},"method":"GET","uri":"{{config.urlCHT}}/horarios-atendimentos/v1/horarios-atendimentos?idFila={{config.botIdentity}}&team=default","responseStatusVariable":"statusIsWorkTime","responseBodyVariable":"bodyIsWorkTime"},"conditions":[]},{"$id":"ecf75b13-2b1e-4f31-aa04-a4a33d34bd9a","$typeOfContent":"","type":"ExecuteScript","$title":"Process \"isWorkTime\"","$invalid":false,"settings":{"function":"run","source":"function run(retornoAPI) {\n    try {\n        const obj = JSON.parse(retornoAPI);\n        return obj.data.isWorkTime;\n    } catch (err) {\n        return false\n    }\n}","inputVariables":["bodyIsWorkTime"],"outputVariable":"isWorkTime","LocalTimeZoneEnabled":false},"conditions":[]},{"type":"TrackEvent","$title":"STATUS API HORARIO","$invalid":false,"settings":{"extras":{},"category":"Status API Horario","action":"{{statusIsWorkTime}}"},"conditions":[]}],"$leavingCustomActions":[],"$inputSuggestions":[],"$defaultOutput":{"stateId":"fallback","$invalid":false},"$tags":[{"id":"blip-tag-d78c4d53-f9b1-4fa6-8bc3-ab55c4aaa79d","label":"ProcessHttp","background":"#7762E3","canChangeBackground":false},{"id":"blip-tag-e003950e-e9d0-4797-9cb6-931a262b883e","label":"ExecuteScript","background":"#FF961E","canChangeBackground":false},{"id":"blip-tag-69ea2436-46b5-42b9-a640-7876cb0b5939","label":"TrackEvent","background":"#61D36F","canChangeBackground":false}],"id":"5a9c72b7-bfaf-4105-86c1-9cf8be316c37","root":false,"$title":"[AH.2.2.0] Api horario atendimento","$position":{"top":"807px","left":"703px"},"$invalidContentActions":false,"$invalidOutputs":false,"$invalidCustomActions":false,"$invalid":false,"isAiGenerated":false},"9a6f3021-b73e-4a50-8ada-691ed5fecfd8":{"$contentActions":[{"action":{"$id":"2bfbd566-a6bd-40a8-8c6f-1c2914248525","$typeOfContent":"chat-state","type":"SendMessage","settings":{"id":"fa4aecac-8402-497e-aa9a-f3dc5a922c43","type":"application/vnd.lime.chatstate+json","content":{"state":"composing","interval":1000}},"$cardContent":{"document":{"id":"fa4aecac-8402-497e-aa9a-f3dc5a922c43","type":"application/vnd.lime.chatstate+json","content":{"state":"composing","interval":1000}},"editable":true,"deletable":true,"position":"left"}},"$invalid":false},{"action":{"$id":"c2f90b7f-40e7-49a0-a578-9587dac0f05f","$typeOfContent":"text","type":"SendMessage","settings":{"id":"2ea5920a-16e7-4c00-b2cd-68f28a90de0f","type":"text/plain","content":"Neste caso, pedimos por gentileza que entre em contato com o seu gerente.\nPara isso, siga as seguintes instruções:\n• Internet Banking:\n1. Acesse a página inicial.\n2. Clique no menu superior direito.\n3. Selecione a opção \"Meu Gerente\".\n4. As informações do gerente serão apresentadas em um card.\n• Mobile:\n1. Vá para a tela inicial.\n2. No canto superior direito, toque no ícone de gerente ao lado esquerdo da lupa.\n3. As informações do gerente serão exibidas.","metadata":{}},"$cardContent":{"document":{"id":"2ea5920a-16e7-4c00-b2cd-68f28a90de0f","type":"text/plain","content":"Neste caso, pedimos por gentileza que entre em contato com o seu gerente.\nPara isso, siga as seguintes instruções:\n• Internet Banking:\n1. Acesse a página inicial.\n2. Clique no menu superior direito.\n3. Selecione a opção \"Meu Gerente\".\n4. As informações do gerente serão apresentadas em um card.\n• Mobile:\n1. Vá para a tela inicial.\n2. No canto superior direito, toque no ícone de gerente ao lado esquerdo da lupa.\n3. As informações do gerente serão exibidas."},"editable":true,"deletable":true,"position":"left"}},"$invalid":false},{"input":{"bypass":true,"$cardContent":{"document":{"id":"84ad3053-d033-4c09-93d8-404f7f0b1a3c","type":"text/plain","textContent":"Entrada do usuário","content":"Entrada do usuário"},"editable":false,"deletable":true,"position":"right","editing":false},"$invalid":false},"$invalid":false}],"$conditionOutputs":[{"stateId":"12bba0f4-d1e2-4c3f-8496-7df481f83955","typeOfStateId":"state","$connId":"con_53","$id":"59360793-dff3-48ad-b1f1-44beb502897d","conditions":[{"source":"context","comparison":"exists","values":[],"variable":"contaSelecionada@doc"}],"$invalid":false}],"$enteringCustomActions":[],"$leavingCustomActions":[],"$inputSuggestions":[],"$defaultOutput":{"stateId":"500a7166-13c4-46cc-ae76-b1230f80203b","$invalid":false,"typeOfStateId":"state"},"isAiGenerated":false,"$tags":[{"id":"blip-tag-c1f2bded-c01b-4fcc-8aeb-b6dcc9396e20","label":"SendMessage","background":"#EE82EE","canChangeBackground":false}],"id":"9a6f3021-b73e-4a50-8ada-691ed5fecfd8","root":false,"$title":"[AH.2.0.1] Finalização segmento emp2","$position":{"top":"592px","left":"259px"},"$invalidContentActions":false,"$invalidOutputs":false,"$invalidCustomActions":false,"$invalid":false},"c7d220bd-2237-49f4-88ec-14c555bf202c":{"$contentActions":[{"input":{"bypass":true,"$cardContent":{"document":{"id":"de0209ba-cc78-4ccc-a44d-8ebb5b84cd0a","type":"text/plain","textContent":"Entrada do usuário","content":"Entrada do usuário"},"editable":false,"deletable":true,"position":"right","editing":false},"$invalid":false},"$invalid":false}],"$conditionOutputs":[],"$enteringCustomActions":[{"$id":"462596bd-3e1f-480a-85b5-4c2e948e4109","$typeOfContent":"","type":"ExecuteScript","$title":"Process \"state\"","$invalid":false,"settings":{"function":"run","source":"function run(previousBlockid, previousStateName, lastInput, intent, serviceName, env) {\n\ttry {\n\t\tlet match = previousStateName.match(/\\[(.*?)\\]/);\n\t\tlet stateNameOrigin = match ? match[1] : previousStateName;\n\n\t\treturn {\n\t\t\tbotOrigin: serviceName,\n\t\t\tstateOrigin: previousBlockid,\n\t\t\tstateNameOrigin,\n\t\t\tbotDestination: `WhatsApp PJ ${env || \"\"}`.trim(),\n\t\t\tstateDestination: 'welcome',\n\t\t\tlastInput,\n\t\t\tintent\n\t\t}\n\t} catch (err) {\n\t\treturn {\n\t\t\tbotOrigin: serviceName,\n\t\t\tstateOrigin: previousBlockid,\n\t\t\tbotDestination: `Bot Main ${env || \"\"}`.trim(),\n\t\t\tstateDestination: 'welcome',\n\t\t\terror: err.message,\n\t\t\tlastInput\n\t\t}\n\t}\n}","inputVariables":["state.previous.id","state.previous.name","input.content","userInput","config.serviceName","config.env"],"outputVariable":"state","LocalTimeZoneEnabled":false},"conditions":[]}],"$leavingCustomActions":[{"$id":"d020a3f2-daee-4595-b129-c1d5f7d88fd6","$typeOfContent":"","type":"Redirect","$title":"Redirecionar a um serviço sending {lastInput}","$invalid":false,"settings":{"context":{"type":"text/plain","value":"atendente"},"address":"{{state@botDestination}}"},"conditions":[]}],"$inputSuggestions":[],"$defaultOutput":{"stateId":"onboarding","$invalid":false,"typeOfStateId":"state"},"isAiGenerated":false,"$tags":[{"id":"blip-tag-4c8d766f-a976-4af5-9735-dbf412123ca5","label":"ExecuteScript","background":"#FF961E","canChangeBackground":false},{"id":"blip-tag-b6b4d1ae-ee80-46f3-87af-3fbb4038cca0","label":"Redirect","background":"#1EA1FF","canChangeBackground":false}],"id":"c7d220bd-2237-49f4-88ec-14c555bf202c","root":false,"$title":"[Redirect] WhatsApp PJ (atendente)","$position":{"top":"758px","left":"1516px"},"$invalidContentActions":false,"$invalidOutputs":false,"$invalidCustomActions":false,"$invalid":false},"105470a0-0131-4cdb-9db2-b60e0997a97b":{"$contentActions":[{"input":{"bypass":true,"$cardContent":{"document":{"id":"3a432035-25be-47a0-9375-c12071e5d655","type":"text/plain","textContent":"Entrada do usuário","content":"Entrada do usuário"},"editable":false,"deletable":true,"position":"right","editing":false},"$invalid":false},"$invalid":false}],"$conditionOutputs":[],"$enteringCustomActions":[{"$id":"c01ef50f-0400-45b9-b882-805edc3533c0","$typeOfContent":"","type":"ExecuteScript","$title":"Process \"state\"","$invalid":false,"settings":{"function":"run","source":"function run(previousBlockid, previousStateName, lastInput, intent, serviceName, env) {\n\ttry {\n\t\treturn {\n\t\t\tbotOrigin: serviceName,\n\t\t\tstateOrigin: previousBlockid,\n\t\t\tstateNameOrigin: previousStateName.replace(/.*\\[(.*?)\\].*/, '$1'),\n\t\t\tbotDestination: `finalizacao ${env || \"\"}`.trim(),\n\t\t\tstateDestination: 'welcome',\n\t\t\tlastInput: lastInput || intent,\n\t\t\tintent\n\t\t}\n\t} catch (error) {\n\t\treturn {\n\t\t\tbotOrigin: serviceName,\n\t\t\tstateOrigin: previousBlockid,\n\t\t\tstateNameOrigin: previousStateName.replace(/.*\\[(.*?)\\].*/, '$1'),\n\t\t\tbotDestination: `Bot Main ${env || \"\"}`.trim(),\n\t\t\tstateDestination: 'welcome',\n\t\t\terror: error.message,\n\t\t\tlastInput\n\t\t}\n\t}\n}","inputVariables":["state.previous.id","state.previous.name","input.content","userInput","config.serviceName","config.env"],"outputVariable":"state","LocalTimeZoneEnabled":false},"conditions":[]}],"$leavingCustomActions":[{"$id":"cc1d6a0c-4326-4288-96bf-aea4570ddbb4","$typeOfContent":"","type":"Redirect","$title":"Redirecionar a um serviço","$invalid":false,"settings":{"context":{"type":"text/plain","value":"{{state@lastInput}}"},"address":"{{state@botDestination}}"},"conditions":[]}],"$inputSuggestions":[],"$defaultOutput":{"stateId":"onboarding","$invalid":false,"typeOfStateId":"state"},"isAiGenerated":false,"$tags":[{"id":"blip-tag-bda1b6d6-f7d4-4215-ac75-f88bbc2b4182","label":"ExecuteScript","background":"#FF961E","canChangeBackground":false},{"id":"blip-tag-892af5e2-483a-4376-999b-74c043a2cd90","label":"Redirect","background":"#1EA1FF","canChangeBackground":false}],"id":"105470a0-0131-4cdb-9db2-b60e0997a97b","root":false,"$title":"[Redirect] To  Finalizacao (Welcome)","$position":{"top":"67px","left":"1052px"},"$invalidContentActions":false,"$invalidOutputs":false,"$invalidCustomActions":false,"$invalid":false},"1d08cfc6-9698-4d24-a308-9bb5e400957f":{"$contentActions":[{"input":{"bypass":true,"$cardContent":{"document":{"id":"98dd806d-c9af-4ade-8243-750f87466651","type":"text/plain","textContent":"Entrada do usuário","content":"Entrada do usuário"},"editable":false,"deletable":true,"position":"right","editing":false},"$invalid":false},"$invalid":false}],"$conditionOutputs":[],"$enteringCustomActions":[],"$leavingCustomActions":[{"$id":"09702f26-b5f2-4f37-9a47-3a2b230b9854","type":"Redirect","$title":"Redirect to \"emp1\"","$invalid":false,"settings":{"context":{"type":"text/plain","value":"{{input.content}}"},"address":"emp1"},"conditions":[]}],"$inputSuggestions":[],"$defaultOutput":{"stateId":"onboarding","$invalid":false,"typeOfStateId":"state"},"isAiGenerated":false,"$tags":[{"id":"blip-tag-24a0b0f3-58f7-44c8-b38e-12f8898e819e","label":"Redirect","background":"#1EA1FF","canChangeBackground":false}],"id":"1d08cfc6-9698-4d24-a308-9bb5e400957f","root":false,"$title":"[Redirect] to Emp1","$position":{"top":"1220px","left":"1026px"},"$invalidContentActions":false,"$invalidOutputs":false,"$invalidCustomActions":false,"$invalid":false},"12bba0f4-d1e2-4c3f-8496-7df481f83955":{"$contentActions":[{"input":{"bypass":true,"$cardContent":{"document":{"id":"805099b3-4e7f-45e0-bd67-34404bac3d14","type":"text/plain","textContent":"Entrada do usuário","content":"Entrada do usuário"},"editable":false,"deletable":true,"position":"right","editing":false},"$invalid":false},"$invalid":false}],"$conditionOutputs":[],"$enteringCustomActions":[],"$leavingCustomActions":[],"$inputSuggestions":[],"$defaultOutput":{"stateId":"105470a0-0131-4cdb-9db2-b60e0997a97b","$invalid":false,"typeOfStateId":"state"},"isAiGenerated":false,"$tags":[],"id":"12bba0f4-d1e2-4c3f-8496-7df481f83955","root":false,"$title":"[GO TO][Redirect] To  Finalizacao (Welcome)","$position":{"top":"381px","left":"259px"},"$invalidContentActions":false,"$invalidOutputs":false,"$invalidCustomActions":false,"$invalid":false},"500a7166-13c4-46cc-ae76-b1230f80203b":{"$contentActions":[{"input":{"bypass":true,"$cardContent":{"document":{"id":"3a432035-25be-47a0-9375-c12071e5d655","type":"text/plain","textContent":"Entrada do usuário","content":"Entrada do usuário"},"editable":false,"deletable":true,"position":"right","editing":false},"$invalid":false},"$invalid":false}],"$conditionOutputs":[],"$enteringCustomActions":[{"$id":"c01ef50f-0400-45b9-b882-805edc3533c0","$typeOfContent":"","type":"ExecuteScript","$title":"Process \"state\"","$invalid":false,"settings":{"function":"run","source":"function run(previousBlockid, previousStateName, lastInput, intent, serviceName, env) {\n\ttry {\n\t\treturn {\n\t\t\tbotOrigin: serviceName,\n\t\t\tstateOrigin: previousBlockid,\n\t\t\tstateNameOrigin: previousStateName.replace(/.*\\[(.*?)\\].*/, '$1'),\n\t\t\tbotDestination: `finalizacao ${env || \"\"}`.trim(),\n\t\t\tstateDestination: '2e47b9c6-7eae-40b5-98ff-7230819d1574',\n\t\t\tlastInput: lastInput || intent,\n\t\t\tintent\n\t\t}\n\t} catch (error) {\n\t\treturn {\n\t\t\tbotOrigin: serviceName,\n\t\t\tstateOrigin: previousBlockid,\n\t\t\tstateNameOrigin: previousStateName.replace(/.*\\[(.*?)\\].*/, '$1'),\n\t\t\tbotDestination: `Bot Main ${env || \"\"}`.trim(),\n\t\t\tstateDestination: 'welcome',\n\t\t\terror: error.message,\n\t\t\tlastInput\n\t\t}\n\t}\n}","inputVariables":["state.previous.id","state.previous.name","input.content","userInput","config.serviceName","config.env"],"outputVariable":"state","LocalTimeZoneEnabled":false},"conditions":[]}],"$leavingCustomActions":[{"$id":"cc1d6a0c-4326-4288-96bf-aea4570ddbb4","$typeOfContent":"","type":"Redirect","$title":"Redirecionar a um serviço","$invalid":false,"settings":{"context":{"type":"text/plain","value":"{{state@lastInput}}"},"address":"{{state@botDestination}}"},"conditions":[]}],"$inputSuggestions":[],"$defaultOutput":{"stateId":"onboarding","$invalid":false,"typeOfStateId":"state"},"isAiGenerated":false,"$tags":[{"id":"blip-tag-1b8bb491-3fe3-4e4a-9a73-0c4099d033d0","label":"ExecuteScript","background":"#FF961E","canChangeBackground":false},{"id":"blip-tag-2c3c2ba5-e244-4bad-bc51-4a88bc7a5842","label":"Redirect","background":"#1EA1FF","canChangeBackground":false}],"id":"500a7166-13c4-46cc-ae76-b1230f80203b","root":false,"$title":"[Redirect] To  Finalizacao (Finalizar)","$position":{"top":"67px","left":"1248px"},"$invalidContentActions":false,"$invalidOutputs":false,"$invalidCustomActions":false,"$invalid":false}},"configuration":{"builder:minimumIntentScore":"0.5","builder:stateTrack":"true","builder:#localTimeZone":"E. South America Standard Time","builder:useTunnelOwnerContext":"true","serviceName":"atendimentohumano","TraceTargetType":"Http","TraceMode":"All","TraceTarget":"https://take-api-beholder.cs.blip.ai/api/traces/betaspdatendimentohumano","urlCHT":"https://api-hml.safra.com.br/chat-assistente","botIdentity":"betaspdatendimentohumano"},"globalActions":{"$contentActions":[],"$conditionOutputs":[],"$enteringCustomActions":[],"$leavingCustomActions":[],"$inputSuggestions":[],"$defaultOutput":{"stateId":"fallback","$invalid":false},"isAiGenerated":false,"$tags":[],"id":"global-actions","$invalidContentActions":false,"$invalidOutputs":false,"$invalidCustomActions":false,"$invalid":false}}